nocycle_singleton/__init__.py
nocycle_singleton/singleton.py
nocycle_singleton-0.0.3.dist-info/METADATA
nocycle_singleton-0.0.3.dist-info/RECORD
nocycle_singleton-0.0.3.dist-info/WHEEL
nocycle_singleton-0.0.3.dist-info/top_level.txt
