Metadata-Version: 2.1
Name: nocycle-singleton
Version: 0.0.3
Summary: A singleton package that can prevent reference cycle
Home-page: https://github.com/pypa/example-project
Author: huangjiangbo
Author-email: huangjiangbo.z@gmail.com
License: UNKNOWN
Platform: UNKNOWN
Classifier: Programming Language :: Python :: 2
Classifier: Programming Language :: Python :: 3
Classifier: License :: OSI Approved :: MIT License
Classifier: Operating System :: OS Independent
